README.md
setup.py
pulumiverse_buildkite/__init__.py
pulumiverse_buildkite/_inputs.py
pulumiverse_buildkite/_utilities.py
pulumiverse_buildkite/get_meta.py
pulumiverse_buildkite/provider.py
pulumiverse_buildkite/pulumi-plugin.json
pulumiverse_buildkite/py.typed
pulumiverse_buildkite.egg-info/PKG-INFO
pulumiverse_buildkite.egg-info/SOURCES.txt
pulumiverse_buildkite.egg-info/dependency_links.txt
pulumiverse_buildkite.egg-info/not-zip-safe
pulumiverse_buildkite.egg-info/requires.txt
pulumiverse_buildkite.egg-info/top_level.txt
pulumiverse_buildkite/agent/__init__.py
pulumiverse_buildkite/agent/agent_token.py
pulumiverse_buildkite/cluster/__init__.py
pulumiverse_buildkite/cluster/cluster.py
pulumiverse_buildkite/cluster/cluster_agent_token.py
pulumiverse_buildkite/cluster/cluster_default_queue.py
pulumiverse_buildkite/cluster/cluster_queue.py
pulumiverse_buildkite/cluster/get_cluster.py
pulumiverse_buildkite/config/__init__.py
pulumiverse_buildkite/config/outputs.py
pulumiverse_buildkite/config/vars.py
pulumiverse_buildkite/organization/__init__.py
pulumiverse_buildkite/organization/banner.py
pulumiverse_buildkite/organization/get_organization.py
pulumiverse_buildkite/organization/organization.py
pulumiverse_buildkite/pipeline/__init__.py
pulumiverse_buildkite/pipeline/_inputs.py
pulumiverse_buildkite/pipeline/get_pipeline.py
pulumiverse_buildkite/pipeline/get_signed_steps.py
pulumiverse_buildkite/pipeline/get_template.py
pulumiverse_buildkite/pipeline/outputs.py
pulumiverse_buildkite/pipeline/pipeline.py
pulumiverse_buildkite/pipeline/schedule.py
pulumiverse_buildkite/pipeline/team.py
pulumiverse_buildkite/pipeline/template.py
pulumiverse_buildkite/team/__init__.py
pulumiverse_buildkite/team/get_team.py
pulumiverse_buildkite/team/member.py
pulumiverse_buildkite/team/team.py
pulumiverse_buildkite/testsuite/__init__.py
pulumiverse_buildkite/testsuite/team.py
pulumiverse_buildkite/testsuite/test_suite.py