Metadata-Version: 2.1
Name: pulumiverse-buildkite
Version: 3.1.5
Summary: A Pulumi package for creating and managing Buildkite resources.
Home-page: https://github.com/pulumiverse/pulumi-buildkite
License: Apache-2.0
Project-URL: Repository, https://github.com/pulumiverse/pulumi-buildkite
Keywords: pulumi buildkite
Platform: UNKNOWN
Requires-Python: >=3.8
